xlsd/__init__.py
xlsd/icons.py
xlsd/path.py
xontrib/xlsd.xsh
xontrib_xlsd-0.1.7.dist-info/LICENSE
xontrib_xlsd-0.1.7.dist-info/METADATA
xontrib_xlsd-0.1.7.dist-info/WHEEL
xontrib_xlsd-0.1.7.dist-info/top_level.txt
xontrib_xlsd-0.1.7.dist-info/RECORD
