Metadata-Version: 2.1
Name: xontrib-xlsd
Version: 0.1.7
Summary: An improved ls for xonsh, inspired by lsd
Home-page: https://github.com/cafehaine/xontrib-xlsd
Author: CaféHaine
Author-email: kilian.guillaume@gmail.com
License: GPLv3
Classifier: Environment :: Console
Classifier: Environment :: Plugins
Classifier: License :: OSI Approved :: GNU General Public License v3 (GPLv3)
Classifier: Operating System :: POSIX
Classifier: Programming Language :: Python :: 3
Requires-Python: >=3.9
License-File: LICENSE
Requires-Dist: xonsh >=0.9.26
Requires-Dist: wcwidth >=0.2.5
